nova_client/__init__.py
nova_client/adapter.py
nova_client/chat_session_client.py
nova_client/client.py
nova_client/actions/signature_verification.py
nova_client/models/__init__.py
nova_client/models/requests.py
nova_client/models/responses.py
nova_client-0.0.5.dist-info/LICENSE
nova_client-0.0.5.dist-info/METADATA
nova_client-0.0.5.dist-info/WHEEL
nova_client-0.0.5.dist-info/top_level.txt
nova_client-0.0.5.dist-info/RECORD
