Metadata-Version: 2.1
Name: nova-client
Version: 0.0.5
Summary: NOVA Machine to Machine Client
Author-email: Serapion GmbH <dev@serapion.net>
Classifier: Programming Language :: Python :: 3
Requires-Python: >=3.12
License-File: LICENSE
Requires-Dist: pydantic <3.0.0,>=2.0.0
Requires-Dist: aiohttp <4.0.0,>=3.8.5
Requires-Dist: fastapi <1.0.0,>=0.103.2
Requires-Dist: authlib <2.0.0,>=1.3.0
Provides-Extra: ci
Requires-Dist: flake8 <8.0.0,>=7.0.0 ; extra == 'ci'
Requires-Dist: pytest <8.0.0,>=7.4.4 ; extra == 'ci'
Requires-Dist: pytest-asyncio <1.0.0,>=0.21.0 ; extra == 'ci'
Requires-Dist: pytest-cov <5.0.0,>=4.1.0 ; extra == 'ci'
Provides-Extra: dev
Requires-Dist: pytest <8.0.0,>=7.4.2 ; extra == 'dev'
Requires-Dist: pytest-asyncio <1.0.0,>=0.21.0 ; extra == 'dev'
Requires-Dist: pytest-cov <5.0.0,>=4.1.0 ; extra == 'dev'
Requires-Dist: pre-commit <4.0.0,>=3.6.0 ; extra == 'dev'
Requires-Dist: python-dotenv <2.0.0,>=1.0.1 ; extra == 'dev'
